toraniko_pandas/__init__.py
toraniko_pandas/extras.py
toraniko_pandas/math.py
toraniko_pandas/model.py
toraniko_pandas/styles.py
toraniko_pandas/utils.py
toraniko_pandas-0.1.2.dist-info/METADATA
toraniko_pandas-0.1.2.dist-info/WHEEL
toraniko_pandas-0.1.2.dist-info/licenses/LICENSE
toraniko_pandas-0.1.2.dist-info/RECORD
