Metadata-Version: 2.4
Name: toraniko_pandas
Version: 0.1.2
Summary: Pandas implementation of institutional-grade multi-factor risk model (Polars original by 0xfdf/toraniko)
Project-URL: Repository, https://github.com/bjrnsa/toraniko-pandas
Project-URL: Issues, https://github.com/bjrnsa/toraniko-pandas/issues
Author-email: Bjørn Aagaard <aagaardbs@gmail.com>
License-Expression: MIT
License-File: LICENSE
Keywords: analysis,data,factor_models,finance,market,pandas,stock,toraniko
Requires-Python: >=3.10
Requires-Dist: cvxpy>=1.6.4
Requires-Dist: ipykernel>=6.29.5
Requires-Dist: lxml>=5.3.1
Requires-Dist: matplotlib>=3.10.0
Requires-Dist: notebook>=7.3.2
Requires-Dist: numpy>=2.2.3
Requires-Dist: pandas>=2.2.3
Requires-Dist: python-dotenv>=1.0.1
Requires-Dist: seaborn>=0.13.2
Requires-Dist: simfin>=1.0.1
Requires-Dist: statsmodels>=0.14.4
Requires-Dist: tqdm>=4.67.1
Requires-Dist: yfinance>=0.2.53
